ooetl/__init__.py
ooetl/docs/Makefile
ooetl/docs/_static/images/classes_uml.graffle
ooetl/docs/_static/images/classes_uml.png
ooetl/docs/conf.py
ooetl/docs/index.rst
ooetl/docs/install.rst
ooetl/docs/intro.rst
ooetl/docs/src/oo_etl.rst
ooetl/docs/tutorial.rst
ooetl/extractors/__init__.py
ooetl/extractors/sparql.py
ooetl/loaders.py
ooetl/tests/__init__.py
ooetl/tests/django.py
ooetl/tests/test_ooetl.py
ooetl/transformations.py
ooetl-1.2.3.dist-info/LICENSE.txt
ooetl-1.2.3.dist-info/WHEEL
ooetl-1.2.3.dist-info/METADATA
ooetl-1.2.3.dist-info/RECORD
