Metadata-Version: 2.1
Name: ooetl
Version: 1.2.3
Summary: Minimal opinionated object oriented ETL framework
Home-page: https://github.com/openpolis/ooetl/
License: MIT
Author: guglielmo
Author-email: guglielmo@openpolis.it
Requires-Python: >=3.7.1,<4.0.0
Classifier: License :: OSI Approved :: MIT License
Classifier: Programming Language :: Python :: 3
Classifier: Programming Language :: Python :: 3.8
Classifier: Programming Language :: Python :: 3.9
Provides-Extra: all
Provides-Extra: elastic
Provides-Extra: html
Provides-Extra: myssql
Provides-Extra: postgresql
Provides-Extra: sparql
Requires-Dist: SPARQLWrapper (>=1.8.5,<2.0.0); extra == "sparql" or extra == "all"
Requires-Dist: SQLAlchemy; extra == "myssql" or extra == "postgresql" or extra == "all"
Requires-Dist: cssselect (>=1.1.0,<2.0.0); extra == "html" or extra == "all"
Requires-Dist: elasticsearch (>=7.13.3,<8.0.0); extra == "elastic" or extra == "all"
Requires-Dist: lxml (>=4.6.3,<5.0.0); extra == "html" or extra == "all"
Requires-Dist: mysqlclient (>=2.0.3,<3.0.0); extra == "myssql" or extra == "all"
Requires-Dist: pandas (>=1.3.0,<2.0.0)
Requires-Dist: psycopg2-binary (>=2.9.1,<3.0.0); extra == "postgresql" or extra == "all"
Requires-Dist: requests (>=2.26.0,<3.0.0)
Project-URL: Repository, https://github.com/openpolis/ooetl/
